kcman/__init__.py
kcman/clients_manager.py
kcman/credentials_manager.py
kcman/group_manager.py
kcman/idp_utils.py
kcman/migration_manager.py
kcman/user_manager.py
kcman-0.1.data/scripts/kcman
kcman-0.1.dist-info/METADATA
kcman-0.1.dist-info/WHEEL
kcman-0.1.dist-info/top_level.txt
kcman-0.1.dist-info/RECORD
